collection/__init__.py
python_collection-1.0.0.dist-info/METADATA
python_collection-1.0.0.dist-info/WHEEL
python_collection-1.0.0.dist-info/top_level.txt
python_collection-1.0.0.dist-info/RECORD
