Metadata-Version: 2.1
Name: python-collection
Version: 1.0.0
Summary: A simple utility structure for python
Home-page: https://github.com/Scientific-Guy/python-collection
License: MIT
Keywords: collection
Platform: UNKNOWN
Classifier: License :: OSI Approved :: MIT License
Classifier: Programming Language :: Python :: 3
Classifier: Programming Language :: Python :: 3.7
